meterbus/__init__.py
meterbus/auxiliary.py
meterbus/core_objects.py
meterbus/data_information_block.py
meterbus/defines.py
meterbus/exceptions.py
meterbus/globals.py
meterbus/serial.py
meterbus/telegram_ack.py
meterbus/telegram_body.py
meterbus/telegram_control.py
meterbus/telegram_field.py
meterbus/telegram_header.py
meterbus/telegram_long.py
meterbus/telegram_short.py
meterbus/telegram_variable_data_record.py
meterbus/value_information_block.py
meterbus/wtelegram_body.py
meterbus/wtelegram_header.py
meterbus/wtelegram_snd_nr.py
meterbus/tools/__init__.py
meterbus/tools/mbus-serial-scan.py
pyMeterBus-0.8.4.dist-info/LICENSE
pyMeterBus-0.8.4.dist-info/METADATA
pyMeterBus-0.8.4.dist-info/WHEEL
pyMeterBus-0.8.4.dist-info/entry_points.txt
pyMeterBus-0.8.4.dist-info/top_level.txt
pyMeterBus-0.8.4.dist-info/RECORD
