Metadata-Version: 2.1
Name: pyMeterBus
Version: 0.8.4
Summary: Python implementation of the Meter-Bus protocol
Home-page: https://github.com/ganehag/pyMeterBus
Author: Mikael Ganehag Brorsson
Author-email: mikael.brorsson@gmail.com
License: BSD-3-Clause
Classifier: Development Status :: 4 - Beta
Classifier: Intended Audience :: Developers
Classifier: License :: OSI Approved :: BSD License
Classifier: Programming Language :: Python :: 3.6
Classifier: Programming Language :: Python :: 3.7
Classifier: Programming Language :: Python :: 3.8
Classifier: Programming Language :: Python :: 3.9
Classifier: Programming Language :: Python :: 3.10
Classifier: Topic :: Software Development :: Libraries
Requires-Python: >=3.6
License-File: LICENSE
Requires-Dist: pyaml
Requires-Dist: pycryptodome
Requires-Dist: pyserial
Requires-Dist: simplejson
